{
    "getObs": {
        "offering": "",
        "procedure": "urn:tds:station.sos:",
        "url": "http://testbedapps-dev.sura.org/thredds/sos/shelf_hypoxia/observations/epa/EPA_H07.nc?request=GetObservation&service=SOS&version=1.0.0&responseFormat=text/xml;schema%3D%22om/1.0.0%22"
    },
    "stations": [
        {
            "H": {
                "spatial": [
                    -93.0835,
                    28.6523
                ],
                "temporal": [
                    "2005-03-30T15:50:59",
                    "2007-08-22T20:20:00"
                ]
            }
        }
    ]
}