{
    "getObs": {
        "offering": "",
        "procedure": "urn:tds:station.sos:",
        "url": "http://testbedapps-dev.sura.org/thredds/sos/shelf_hypoxia/observations/epa/EPA_E02a.nc?request=GetObservation&service=SOS&version=1.0.0&responseFormat=text/xml;schema%3D%22om/1.0.0%22"
    },
    "stations": [
        {
            "E02a": {
                "spatial": [
                    -90.4153,
                    28.4166
                ],
                "temporal": [
                    "2007-08-21T18:56:59",
                    "2007-08-21T18:56:59"
                ]
            }
        }
    ]
}