{
    "getObs": {
        "offering": "",
        "procedure": "urn:tds:station.sos:",
        "url": "http://testbedapps-dev.sura.org/thredds/sos/shelf_hypoxia/observations/mch/MCH_ma008c15lowercase.nc?request=GetObservation&service=SOS&version=1.0.0&responseFormat=text/xml;schema%3D%22om/1.0.0%22"
    },
    "stations": [
        {
            "ma008c15": {
                "spatial": [
                    -91.9091,
                    29.1206
                ],
                "temporal": [
                    "2007-09-07T18:00:59",
                    "2007-09-07T18:00:59"
                ]
            }
        }
    ]
}