{
    "getObs": {
        "offering": "",
        "procedure": "urn:tds:station.sos:",
        "url": "http://testbedapps-dev.sura.org/thredds/sos/shelf_hypoxia/observations/seamap/SEAMAP_WD18.nc?request=GetObservation&service=SOS&version=1.0.0&responseFormat=text/xml;schema%3D%22om/1.0.0%22"
    },
    "stations": [
        {
            "WD18": {
                "spatial": [
                    -95.074,
                    28.533
                ],
                "temporal": [
                    "2004-07-04T10:07:00",
                    "2006-07-06T20:18:59"
                ]
            }
        }
    ]
}