{
    "getObs": {
        "offering": "",
        "procedure": "urn:tds:station.sos:",
        "url": "http://testbedapps-dev.sura.org/thredds/sos/shelf_hypoxia/observations/seamap/SEAMAP_11436298.nc?request=GetObservation&service=SOS&version=1.0.0&responseFormat=text/xml;schema%3D%22om/1.0.0%22"
    },
    "stations": [
        {
            "11436298": {
                "spatial": [
                    -95.7745,
                    28.6185
                ],
                "temporal": [
                    "2004-05-19T19:22:46",
                    "2004-05-19T19:22:46"
                ]
            }
        }
    ]
}