{
    "getObs": {
        "offering": "",
        "procedure": "urn:tds:station.sos:",
        "url": "http://testbedapps-dev.sura.org/thredds/sos/shelf_hypoxia/observations/seamap/SEAMAP_114.nc?request=GetObservation&service=SOS&version=1.0.0&responseFormat=text/xml;schema%3D%22om/1.0.0%22"
    },
    "stations": [
        {
            "114": {
                "spatial": [
                    -95.41300000000001,
                    28.149500000000003
                ],
                "temporal": [
                    "2007-06-26T11:38:23",
                    "2008-06-27T00:51:55"
                ]
            }
        }
    ]
}