{
    "getObs": {
        "offering": "",
        "procedure": "urn:tds:station.sos:",
        "url": "http://testbedapps-dev.sura.org/thredds/sos/shelf_hypoxia/observations/seamap/SEAMAP_106.nc?request=GetObservation&service=SOS&version=1.0.0&responseFormat=text/xml;schema%3D%22om/1.0.0%22"
    },
    "stations": [
        {
            "1": {
                "spatial": [
                    -90.733,
                    28.887500000000003
                ],
                "temporal": [
                    "2007-06-25T16:37:34",
                    "2008-06-26T01:06:10"
                ]
            }
        }
    ]
}