{
    "getObs": {
        "offering": "",
        "procedure": "urn:tds:station.sos:",
        "url": "http://testbedapps-dev.sura.org/thredds/sos/shelf_hypoxia/observations/seamap/SEAMAP_00238.nc?request=GetObservation&service=SOS&version=1.0.0&responseFormat=text/xml;schema%3D%22om/1.0.0%22"
    },
    "stations": [
        {
            "00238": {
                "spatial": [
                    -94.23534,
                    28.83333
                ],
                "temporal": [
                    "2004-07-11T20:09:00",
                    "2008-07-12T01:44:59"
                ]
            }
        }
    ]
}