{
    "getObs": {
        "offering": "",
        "procedure": "urn:tds:station.sos:",
        "url": "http://testbedapps-dev.sura.org/thredds/sos/shelf_hypoxia/observations/seamap/SEAMAP_063.nc?request=GetObservation&service=SOS&version=1.0.0&responseFormat=text/xml;schema%3D%22om/1.0.0%22"
    },
    "stations": [
        {
            "063": {
                "spatial": [
                    -91.99633,
                    28.5005
                ],
                "temporal": [
                    "2008-06-20T06:31:18",
                    "2008-06-20T06:31:18"
                ]
            }
        }
    ]
}