{
    "getObs": {
        "offering": "",
        "procedure": "urn:tds:station.sos:",
        "url": "http://testbedapps-dev.sura.org/thredds/sos/shelf_hypoxia/observations/seamap/SEAMAP_00094.nc?request=GetObservation&service=SOS&version=1.0.0&responseFormat=text/xml;schema%3D%22om/1.0.0%22"
    },
    "stations": [
        {
            "00094": {
                "spatial": [
                    -96.96917,
                    27.4075
                ],
                "temporal": [
                    "2004-06-26T03:02:59",
                    "2007-06-21T14:00:00"
                ]
            }
        }
    ]
}