{
    "getObs": {
        "offering": "",
        "procedure": "urn:tds:station.sos:",
        "url": "http://testbedapps-dev.sura.org/thredds/sos/shelf_hypoxia/observations/seamap/SEAMAP_00185.nc?request=GetObservation&service=SOS&version=1.0.0&responseFormat=text/xml;schema%3D%22om/1.0.0%22"
    },
    "stations": [
        {
            "0": {
                "spatial": [
                    -95.131,
                    28.216500000000003
                ],
                "temporal": [
                    "2004-07-07T05:34:00",
                    "2004-07-07T05:34:00"
                ]
            }
        }
    ]
}