{
    "getObs": {
        "offering": "",
        "procedure": "urn:tds:station.sos:",
        "url": "http://testbedapps-dev.sura.org/thredds/sos/imeds/measurement/watlev_CRMS_2005.nc?request=GetObservation&service=SOS&version=1.0.0&responseFormat=text/xml;schema%3D%22om/1.0.0%22"
    },
    "stations": [
        {
            "CRMS_BA04-07": {
                "spatial": [
                    -89.7802963256836,
                    29.524084091186523
                ],
                "temporal": [
                    "2005-08-01T00:00:00",
                    "2005-10-01T00:00:00"
                ]
            }
        },
        {
            "CRMS_BA04-10": {
                "spatial": [
                    -89.81716918945312,
                    29.499990463256836
                ],
                "temporal": [
                    "2005-08-01T00:00:00",
                    "2005-10-01T00:00:00"
                ]
            }
        },
        {
            "CRMS_BA04-17": {
                "spatial": [
                    -89.82440948486328,
                    29.520612716674805
                ],
                "temporal": [
                    "2005-08-01T00:00:00",
                    "2005-10-01T00:00:00"
                ]
            }
        },
        {
            "CRMS_BA04-55": {
                "spatial": [
                    -89.75529479980469,
                    29.500608444213867
                ],
                "temporal": [
                    "2005-08-01T00:00:00",
                    "2005-10-01T00:00:00"
                ]
            }
        },
        {
            "CRMS_BA04-56": {
                "spatial": [
                    -89.76139068603516,
                    29.47828483581543
                ],
                "temporal": [
                    "2005-08-01T00:00:00",
                    "2005-10-01T00:00:00"
                ]
            }
        },
        {
            "CRMS_BS08-09": {
                "spatial": [
                    -89.86113739013672,
                    29.686342239379883
                ],
                "temporal": [
                    "2005-08-01T00:00:00",
                    "2005-10-01T00:00:00"
                ]
            }
        },
        {
            "CRMS_BS08-13": {
                "spatial": [
                    -89.7023696899414,
                    29.6572265625
                ],
                "temporal": [
                    "2005-08-01T00:00:00",
                    "2005-10-01T00:00:00"
                ]
            }
        },
        {
            "CRMS_CS02-05": {
                "spatial": [
                    -93.46627044677734,
                    29.964385986328125
                ],
                "temporal": [
                    "2005-08-01T00:00:00",
                    "2005-10-01T00:00:00"
                ]
            }
        },
        {
            "CRMS_CS20-03": {
                "spatial": [
                    -93.3993148803711,
                    29.808704376220703
                ],
                "temporal": [
                    "2005-08-01T00:00:00",
                    "2005-10-01T00:00:00"
                ]
            }
        },
        {
            "CRMS_CS20-07": {
                "spatial": [
                    -93.44805908203125,
                    29.830095291137695
                ],
                "temporal": [
                    "2005-08-01T00:00:00",
                    "2005-10-01T00:00:00"
                ]
            }
        },
        {
            "CRMS_CS20-09": {
                "spatial": [
                    -93.42810821533203,
                    29.82998275756836
                ],
                "temporal": [
                    "2005-08-01T00:00:00",
                    "2005-10-01T00:00:00"
                ]
            }
        },
        {
            "CRMS_CS20-14R": {
                "spatial": [
                    -93.39655303955078,
                    29.80691909790039
                ],
                "temporal": [
                    "2005-08-01T00:00:00",
                    "2005-10-01T00:00:00"
                ]
            }
        },
        {
            "CRMS_CS20-15R": {
                "spatial": [
                    -93.45144653320312,
                    29.864042282104492
                ],
                "temporal": [
                    "2005-08-01T00:00:00",
                    "2005-10-01T00:00:00"
                ]
            }
        },
        {
            "CRMS_CS20-17": {
                "spatial": [
                    -93.43194580078125,
                    29.804658889770508
                ],
                "temporal": [
                    "2005-08-01T00:00:00",
                    "2005-10-01T00:00:00"
                ]
            }
        },
        {
            "CRMS_BA01-01": {
                "spatial": [
                    -90.35877990722656,
                    29.701494216918945
                ],
                "temporal": [
                    "2005-08-01T00:00:00",
                    "2005-10-01T00:00:00"
                ]
            }
        },
        {
            "CRMS_BA01-02": {
                "spatial": [
                    -90.1695785522461,
                    29.81676483154297
                ],
                "temporal": [
                    "2005-08-01T00:00:00",
                    "2005-10-01T00:00:00"
                ]
            }
        },
        {
            "CRMS_BA01-03": {
                "spatial": [
                    -90.23445129394531,
                    29.79620933532715
                ],
                "temporal": [
                    "2005-08-01T00:00:00",
                    "2005-10-01T00:00:00"
                ]
            }
        },
        {
            "CRMS_BA01-04": {
                "spatial": [
                    -90.29158020019531,
                    29.770973205566406
                ],
                "temporal": [
                    "2005-08-01T00:00:00",
                    "2005-10-01T00:00:00"
                ]
            }
        },
        {
            "CRMS_BA01-07": {
                "spatial": [
                    -90.16131591796875,
                    29.573383331298828
                ],
                "temporal": [
                    "2005-08-01T00:00:00",
                    "2005-10-01T00:00:00"
                ]
            }
        },
        {
            "CRMS_BA01-09": {
                "spatial": [
                    -90.3409194946289,
                    29.63100814819336
                ],
                "temporal": [
                    "2005-08-01T00:00:00",
                    "2005-10-01T00:00:00"
                ]
            }
        },
        {
            "CRMS_BA01-10": {
                "spatial": [
                    -90.11031341552734,
                    29.66740608215332
                ],
                "temporal": [
                    "2005-08-01T00:00:00",
                    "2005-10-01T00:00:00"
                ]
            }
        },
        {
            "CRMS_BA02-54": {
                "spatial": [
                    -90.23030853271484,
                    29.553743362426758
                ],
                "temporal": [
                    "2005-08-01T00:00:00",
                    "2005-10-01T00:00:00"
                ]
            }
        },
        {
            "CRMS_BA02-56": {
                "spatial": [
                    -90.27157592773438,
                    29.560556411743164
                ],
                "temporal": [
                    "2005-08-01T00:00:00",
                    "2005-10-01T00:00:00"
                ]
            }
        },
        {
            "CRMS_BA02-57": {
                "spatial": [
                    -90.26338958740234,
                    29.489662170410156
                ],
                "temporal": [
                    "2005-08-01T00:00:00",
                    "2005-10-01T00:00:00"
                ]
            }
        },
        {
            "CRMS_TE26-03": {
                "spatial": [
                    -91.29560852050781,
                    29.29425621032715
                ],
                "temporal": [
                    "2005-08-01T00:00:00",
                    "2005-10-01T00:00:00"
                ]
            }
        },
        {
            "CRMS_TE26-05": {
                "spatial": [
                    -91.27023315429688,
                    29.280555725097656
                ],
                "temporal": [
                    "2005-08-01T00:00:00",
                    "2005-10-01T00:00:00"
                ]
            }
        },
        {
            "CRMS_TE28-01": {
                "spatial": [
                    -91.00090026855469,
                    29.385780334472656
                ],
                "temporal": [
                    "2005-08-01T00:00:00",
                    "2005-10-01T00:00:00"
                ]
            }
        },
        {
            "CRMS_TE28-02": {
                "spatial": [
                    -90.95728302001953,
                    29.407306671142578
                ],
                "temporal": [
                    "2005-08-01T00:00:00",
                    "2005-10-01T00:00:00"
                ]
            }
        },
        {
            "CRMS_TE28-03": {
                "spatial": [
                    -90.96513366699219,
                    29.36959457397461
                ],
                "temporal": [
                    "2005-08-01T00:00:00",
                    "2005-10-01T00:00:00"
                ]
            }
        },
        {
            "CRMS_TE28-07R": {
                "spatial": [
                    -90.96672058105469,
                    29.417268753051758
                ],
                "temporal": [
                    "2005-08-01T00:00:00",
                    "2005-10-01T00:00:00"
                ]
            }
        },
        {
            "CRMS_CS23-01R": {
                "spatial": [
                    -93.3816146850586,
                    29.90889549255371
                ],
                "temporal": [
                    "2005-08-01T00:00:00",
                    "2005-10-01T00:00:00"
                ]
            }
        },
        {
            "CRMS_CS23-03": {
                "spatial": [
                    -93.529296875,
                    29.879209518432617
                ],
                "temporal": [
                    "2005-08-01T00:00:00",
                    "2005-10-01T00:00:00"
                ]
            }
        },
        {
            "CRMS_CS23-05": {
                "spatial": [
                    -93.52888488769531,
                    29.962486267089844
                ],
                "temporal": [
                    "2005-08-01T00:00:00",
                    "2005-10-01T00:00:00"
                ]
            }
        },
        {
            "CRMS_ME04-06": {
                "spatial": [
                    -92.2603530883789,
                    29.749174118041992
                ],
                "temporal": [
                    "2005-08-01T00:00:00",
                    "2005-10-01T00:00:00"
                ]
            }
        },
        {
            "CRMS_ME04-26R": {
                "spatial": [
                    -92.26744079589844,
                    29.670589447021484
                ],
                "temporal": [
                    "2005-08-01T00:00:00",
                    "2005-10-01T00:00:00"
                ]
            }
        },
        {
            "CRMS_ME04-29": {
                "spatial": [
                    -92.28668212890625,
                    29.652790069580078
                ],
                "temporal": [
                    "2005-08-01T00:00:00",
                    "2005-10-01T00:00:00"
                ]
            }
        },
        {
            "CRMS_ME04-43R": {
                "spatial": [
                    -92.25127410888672,
                    29.664121627807617
                ],
                "temporal": [
                    "2005-08-01T00:00:00",
                    "2005-10-01T00:00:00"
                ]
            }
        },
        {
            "CRMS_TE28-218": {
                "spatial": [
                    -90.95852661132812,
                    29.407819747924805
                ],
                "temporal": [
                    "2005-08-01T00:00:00",
                    "2005-10-01T00:00:00"
                ]
            }
        },
        {
            "CRMS_TE26-01R": {
                "spatial": [
                    -91.24824523925781,
                    29.353761672973633
                ],
                "temporal": [
                    "2005-08-01T00:00:00",
                    "2005-10-01T00:00:00"
                ]
            }
        },
        {
            "CRMS_TE26-02R": {
                "spatial": [
                    -91.31312561035156,
                    29.294889450073242
                ],
                "temporal": [
                    "2005-08-01T00:00:00",
                    "2005-10-01T00:00:00"
                ]
            }
        },
        {
            "CRMS_BA01-14": {
                "spatial": [
                    -90.3167495727539,
                    29.85221290588379
                ],
                "temporal": [
                    "2005-08-01T00:00:00",
                    "2005-10-01T00:00:00"
                ]
            }
        },
        {
            "CRMS_BA01-15": {
                "spatial": [
                    -90.29135131835938,
                    29.77082633972168
                ],
                "temporal": [
                    "2005-08-01T00:00:00",
                    "2005-10-01T00:00:00"
                ]
            }
        },
        {
            "CRMS_BA01-16": {
                "spatial": [
                    -90.31673431396484,
                    29.852663040161133
                ],
                "temporal": [
                    "2005-08-01T00:00:00",
                    "2005-10-01T00:00:00"
                ]
            }
        },
        {
            "CRMS_BA02-104": {
                "spatial": [
                    -90.22705078125,
                    29.549076080322266
                ],
                "temporal": [
                    "2005-08-01T00:00:00",
                    "2005-10-01T00:00:00"
                ]
            }
        },
        {
            "CRMS_BA02-105": {
                "spatial": [
                    -90.22704315185547,
                    29.549074172973633
                ],
                "temporal": [
                    "2005-08-01T00:00:00",
                    "2005-10-01T00:00:00"
                ]
            }
        },
        {
            "CRMS_TV04-04R": {
                "spatial": [
                    -91.60816955566406,
                    29.727985382080078
                ],
                "temporal": [
                    "2005-08-01T00:00:00",
                    "2005-10-01T00:00:00"
                ]
            }
        },
        {
            "CRMS_BA02-108": {
                "spatial": [
                    -90.22744750976562,
                    29.552711486816406
                ],
                "temporal": [
                    "2005-08-01T00:00:00",
                    "2005-10-01T00:00:00"
                ]
            }
        },
        {
            "CRMS_BA02-109": {
                "spatial": [
                    -90.2274398803711,
                    29.552711486816406
                ],
                "temporal": [
                    "2005-08-01T00:00:00",
                    "2005-10-01T00:00:00"
                ]
            }
        },
        {
            "CRMS_BA03C-16": {
                "spatial": [
                    -90.01628112792969,
                    29.686723709106445
                ],
                "temporal": [
                    "2005-08-01T00:00:00",
                    "2005-10-01T00:00:00"
                ]
            }
        },
        {
            "CRMS_BA03C-60": {
                "spatial": [
                    -90.08296203613281,
                    29.699939727783203
                ],
                "temporal": [
                    "2005-08-01T00:00:00",
                    "2005-10-01T00:00:00"
                ]
            }
        },
        {
            "CRMS_BA03C-61": {
                "spatial": [
                    -90.03367614746094,
                    29.623912811279297
                ],
                "temporal": [
                    "2005-08-01T00:00:00",
                    "2005-10-01T00:00:00"
                ]
            }
        },
        {
            "CRMS_DCPTE03": {
                "spatial": [
                    -90.72944641113281,
                    29.384443283081055
                ],
                "temporal": [
                    "2005-08-01T00:00:00",
                    "2005-10-01T00:00:00"
                ]
            }
        },
        {
            "CRMS_DCPBS05": {
                "spatial": [
                    -89.71944427490234,
                    29.70805549621582
                ],
                "temporal": [
                    "2005-08-01T00:00:00",
                    "2005-10-01T00:00:00"
                ]
            }
        },
        {
            "CRMS_DCPBS04": {
                "spatial": [
                    -89.70388793945312,
                    29.570554733276367
                ],
                "temporal": [
                    "2005-08-01T00:00:00",
                    "2005-10-01T00:00:00"
                ]
            }
        },
        {
            "CRMS_DCPBS06": {
                "spatial": [
                    -89.9375,
                    29.78416633605957
                ],
                "temporal": [
                    "2005-08-01T00:00:00",
                    "2005-10-01T00:00:00"
                ]
            }
        },
        {
            "CRMS_DCPBS03": {
                "spatial": [
                    -89.61444091796875,
                    29.592222213745117
                ],
                "temporal": [
                    "2005-08-01T00:00:00",
                    "2005-10-01T00:00:00"
                ]
            }
        },
        {
            "CRMS_TV14-01": {
                "spatial": [
                    -91.75403594970703,
                    29.571022033691406
                ],
                "temporal": [
                    "2005-08-01T00:00:00",
                    "2005-10-01T00:00:00"
                ]
            }
        },
        {
            "CRMS_TV14-03R": {
                "spatial": [
                    -91.77191162109375,
                    29.524065017700195
                ],
                "temporal": [
                    "2005-08-01T00:00:00",
                    "2005-10-01T00:00:00"
                ]
            }
        },
        {
            "CRMS_CS27-25": {
                "spatial": [
                    -93.60722351074219,
                    30.03416633605957
                ],
                "temporal": [
                    "2005-08-01T00:00:00",
                    "2005-10-01T00:00:00"
                ]
            }
        },
        {
            "CRMS_TV04-03": {
                "spatial": [
                    -91.60733795166016,
                    29.690765380859375
                ],
                "temporal": [
                    "2005-08-01T00:00:00",
                    "2005-10-01T00:00:00"
                ]
            }
        },
        {
            "CRMS_ME11-01R": {
                "spatial": [
                    -92.87540435791016,
                    29.838729858398438
                ],
                "temporal": [
                    "2005-08-01T00:00:00",
                    "2005-10-01T00:00:00"
                ]
            }
        },
        {
            "CRMS_PO24-01": {
                "spatial": [
                    -89.61483764648438,
                    29.819761276245117
                ],
                "temporal": [
                    "2005-08-01T00:00:00",
                    "2005-10-01T00:00:00"
                ]
            }
        },
        {
            "CRMS_PO24-02": {
                "spatial": [
                    -89.61129760742188,
                    29.8179874420166
                ],
                "temporal": [
                    "2005-08-01T00:00:00",
                    "2005-10-01T00:00:00"
                ]
            }
        },
        {
            "CRMS_PO24-04": {
                "spatial": [
                    -89.65723419189453,
                    29.820024490356445
                ],
                "temporal": [
                    "2005-08-01T00:00:00",
                    "2005-10-01T00:00:00"
                ]
            }
        },
        {
            "CRMS_PO24-05": {
                "spatial": [
                    -89.64575958251953,
                    29.8341121673584
                ],
                "temporal": [
                    "2005-08-01T00:00:00",
                    "2005-10-01T00:00:00"
                ]
            }
        },
        {
            "CRMS_BS03A-02": {
                "spatial": [
                    -89.88059997558594,
                    29.79791259765625
                ],
                "temporal": [
                    "2005-08-01T00:00:00",
                    "2005-10-01T00:00:00"
                ]
            }
        },
        {
            "CRMS_BS03A-03": {
                "spatial": [
                    -89.93765258789062,
                    29.801454544067383
                ],
                "temporal": [
                    "2005-08-01T00:00:00",
                    "2005-10-01T00:00:00"
                ]
            }
        },
        {
            "CRMS_BS03A-66R": {
                "spatial": [
                    -89.92418670654297,
                    29.736909866333008
                ],
                "temporal": [
                    "2005-08-01T00:00:00",
                    "2005-10-01T00:00:00"
                ]
            }
        },
        {
            "CRMS_DCPBA03": {
                "spatial": [
                    -90.31777954101562,
                    29.91694450378418
                ],
                "temporal": [
                    "2005-08-01T00:00:00",
                    "2005-10-01T00:00:00"
                ]
            }
        },
        {
            "CRMS_DCPBA05": {
                "spatial": [
                    -90.18319702148438,
                    29.766611099243164
                ],
                "temporal": [
                    "2005-08-01T00:00:00",
                    "2005-10-01T00:00:00"
                ]
            }
        },
        {
            "CRMS_DCPBA04": {
                "spatial": [
                    -90.20471954345703,
                    29.85527801513672
                ],
                "temporal": [
                    "2005-08-01T00:00:00",
                    "2005-10-01T00:00:00"
                ]
            }
        },
        {
            "CRMS_DCPBA06": {
                "spatial": [
                    -90.0111083984375,
                    29.483055114746094
                ],
                "temporal": [
                    "2005-08-01T00:00:00",
                    "2005-10-01T00:00:00"
                ]
            }
        },
        {
            "CRMS_DCPBA07": {
                "spatial": [
                    -90.0999984741211,
                    29.46666717529297
                ],
                "temporal": [
                    "2005-08-01T00:00:00",
                    "2005-10-01T00:00:00"
                ]
            }
        },
        {
            "CRMS_DCPBA08": {
                "spatial": [
                    -89.94049835205078,
                    29.324724197387695
                ],
                "temporal": [
                    "2005-08-01T00:00:00",
                    "2005-10-01T00:00:00"
                ]
            }
        },
        {
            "CRMS_DCPBS09": {
                "spatial": [
                    -89.90916442871094,
                    29.856666564941406
                ],
                "temporal": [
                    "2005-08-01T00:00:00",
                    "2005-10-01T00:00:00"
                ]
            }
        },
        {
            "CRMS_ME04-143R": {
                "spatial": [
                    -92.36750030517578,
                    29.7194766998291
                ],
                "temporal": [
                    "2005-08-01T00:00:00",
                    "2005-10-01T00:00:00"
                ]
            }
        },
        {
            "CRMS_CS31-02": {
                "spatial": [
                    -93.57066345214844,
                    29.77830696105957
                ],
                "temporal": [
                    "2005-08-01T00:00:00",
                    "2005-10-01T00:00:00"
                ]
            }
        },
        {
            "CRMS_CS31-03": {
                "spatial": [
                    -93.51327514648438,
                    29.770999908447266
                ],
                "temporal": [
                    "2005-08-01T00:00:00",
                    "2005-10-01T00:00:00"
                ]
            }
        },
        {
            "CRMS_CS31-01": {
                "spatial": [
                    -93.5298080444336,
                    29.770832061767578
                ],
                "temporal": [
                    "2005-08-01T00:00:00",
                    "2005-10-01T00:00:00"
                ]
            }
        },
        {
            "CRMS_TV04-22": {
                "spatial": [
                    -91.56988525390625,
                    29.66752815246582
                ],
                "temporal": [
                    "2005-08-01T00:00:00",
                    "2005-10-01T00:00:00"
                ]
            }
        },
        {
            "CRMS_BAFS-17SF": {
                "spatial": [
                    -89.89694213867188,
                    29.122873306274414
                ],
                "temporal": [
                    "2005-08-01T00:00:00",
                    "2005-10-01T00:00:00"
                ]
            }
        },
        {
            "CRMS_BAFS-17BT": {
                "spatial": [
                    -89.89694213867188,
                    29.12287139892578
                ],
                "temporal": [
                    "2005-08-01T00:00:00",
                    "2005-10-01T00:00:00"
                ]
            }
        },
        {
            "CRMS_ME16-06": {
                "spatial": [
                    -92.56803131103516,
                    29.617387771606445
                ],
                "temporal": [
                    "2005-08-01T00:00:00",
                    "2005-10-01T00:00:00"
                ]
            }
        },
        {
            "CRMS_TV14-23": {
                "spatial": [
                    -91.77349090576172,
                    29.55756378173828
                ],
                "temporal": [
                    "2005-08-01T00:00:00",
                    "2005-10-01T00:00:00"
                ]
            }
        },
        {
            "CRMS_CS20-106": {
                "spatial": [
                    -93.45320892333984,
                    29.783000946044922
                ],
                "temporal": [
                    "2005-08-01T00:00:00",
                    "2005-10-01T00:00:00"
                ]
            }
        },
        {
            "CRMS_TV14-04R": {
                "spatial": [
                    -91.8077392578125,
                    29.587682723999023
                ],
                "temporal": [
                    "2005-08-01T00:00:00",
                    "2005-10-01T00:00:00"
                ]
            }
        },
        {
            "CRMS_PO24-03": {
                "spatial": [
                    -89.65575408935547,
                    29.82175064086914
                ],
                "temporal": [
                    "2005-08-01T00:00:00",
                    "2005-10-01T00:00:00"
                ]
            }
        },
        {
            "CRMS_BS03A-01": {
                "spatial": [
                    -89.95433807373047,
                    29.827594757080078
                ],
                "temporal": [
                    "2005-08-01T00:00:00",
                    "2005-10-01T00:00:00"
                ]
            }
        },
        {
            "CRMS_BS03A-04": {
                "spatial": [
                    -89.96261596679688,
                    29.788650512695312
                ],
                "temporal": [
                    "2005-08-01T00:00:00",
                    "2005-10-01T00:00:00"
                ]
            }
        },
        {
            "CRMS_BS03A-07R": {
                "spatial": [
                    -89.87980651855469,
                    29.837997436523438
                ],
                "temporal": [
                    "2005-08-01T00:00:00",
                    "2005-10-01T00:00:00"
                ]
            }
        }
    ]
}